gray2color/__init__.py
gray2color/gray2color.py
gray2color/utils/__init__.py
gray2color/utils/ade20k.py
gray2color/utils/cityscape.py
gray2color/utils/gray2rgb.py
gray2color/utils/lip.py
gray2color/utils/pannuke.py
gray2color/utils/pascal.py
gray2color/utils/vistas.py
gray2color-0.4.1.dist-info/METADATA
gray2color-0.4.1.dist-info/WHEEL
gray2color-0.4.1.dist-info/top_level.txt
gray2color-0.4.1.dist-info/RECORD
