Metadata-Version: 2.1
Name: gray2color
Version: 0.4.1
Summary: Convert your grayscale semantic masks (vistas/cityscape style) to RGB colored masks wiht built-in or custom pallets
Home-page: https://github.com/Mr-TalhaIlyas/Converting-Grayscale-Semantic-Masks-to-Color
Author: Talha Ilyas
Author-email: mr.talhailyas@gmail.com
License: UNKNOWN
Keywords: python,gray2rgb,gray2color,grayscale to rgb,color pallets,cityscapevistas,lip,ade20k,pannuke,pascal_voc
Platform: UNKNOWN
Classifier: Intended Audience :: Education
Classifier: Programming Language :: Python :: 3
Classifier: License :: OSI Approved :: MIT License
Classifier: Operating System :: OS Independent
